dj_tracker/logging.py
dj_tracker/promise.py
dj_tracker/field_descriptors.py
dj_tracker/traceback.cpython-310-darwin.so
dj_tracker/models.py
dj_tracker/traceback.c
dj_tracker/profile.py
dj_tracker/hash_utils.c
dj_tracker/constants.py
dj_tracker/db_router.py
dj_tracker/pythoncapi_compat.h
dj_tracker/collector.py
dj_tracker/__init__.py
dj_tracker/traceback.pyx
dj_tracker/cache_utils.pyx
dj_tracker/test.py
dj_tracker/apps.py
dj_tracker/hash_utils.cpython-310-darwin.so
dj_tracker/cache_utils.pxd
dj_tracker/hash_utils.pyx
dj_tracker/context.py
dj_tracker/cache_utils.cpython-310-darwin.so
dj_tracker/tracker.py
dj_tracker/datastructures.py
dj_tracker/urls.py
dj_tracker/cache_utils.c
dj_tracker/middleware.py
dj_tracker/views.py
dj_tracker/templatetags/__init__.py
dj_tracker/templatetags/dj_tracker.py
dj_tracker/migrations/__init__.py
dj_tracker/migrations/0001_initial.py
dj_tracker/static/dj_tracker/css/main.css
dj_tracker/static/dj_tracker/js/query_group.js
dj_tracker/templates/dj_tracker/home.html
dj_tracker/templates/dj_tracker/base.html
dj_tracker/templates/dj_tracker/list.html
dj_tracker/templates/dj_tracker/requests.html
dj_tracker/templates/dj_tracker/query_groups.html
dj_tracker/templates/dj_tracker/queries.html
dj_tracker/templates/dj_tracker/query_group.html
dj_tracker/templates/dj_tracker/query.html
dj_tracker/templates/dj_tracker/includes/pagination.html
dj_tracker/templates/dj_tracker/includes/listing.html
dj_tracker/templates/dj_tracker/includes/query.html
django_trackings-0.7.0a1.dist-info/RECORD
django_trackings-0.7.0a1.dist-info/LICENSE
django_trackings-0.7.0a1.dist-info/WHEEL
django_trackings-0.7.0a1.dist-info/top_level.txt
django_trackings-0.7.0a1.dist-info/METADATA
