Metadata-Version: 2.1
Name: django_trackings
Version: 0.7.0a1
Summary: A Django app that tracks your queries to help optimize them.
Home-page: https://github.com/tijani-dia/dj-tracker/
Author: Tidiane Dia
Author-email: atdia97@gmail.com
License: BSD-3-Clause
Project-URL: Documentation, https://tijani-dia.github.io/dj-tracker/
Project-URL: Source, https://github.com/tijani-dia/dj-tracker/
Project-URL: Issue tracker, https://github.com/tijani-dia/dj-tracker/issues/
Classifier: Development Status :: 3 - Alpha
Classifier: Environment :: Web Environment
Classifier: Framework :: Django
Classifier: Intended Audience :: Developers
Classifier: License :: OSI Approved :: BSD License
Classifier: Programming Language :: Python :: 3
Classifier: Programming Language :: Python :: 3 :: Only
Requires-Python: >=3.8
License-File: LICENSE
Requires-Dist: django>=3.2
Requires-Dist: django-filter
Provides-Extra: dev
Requires-Dist: Cython==3.0.11; extra == "dev"
Requires-Dist: autoflake; extra == "dev"
Requires-Dist: black>=23.1; extra == "dev"
Requires-Dist: factory-boy; extra == "dev"
Requires-Dist: flake8; extra == "dev"
Requires-Dist: isort; extra == "dev"
Requires-Dist: pytailwindcss; extra == "dev"
Provides-Extra: docs
Requires-Dist: mkdocs; extra == "docs"
Requires-Dist: mkdocs-material; extra == "docs"
Provides-Extra: test
Requires-Dist: factory-boy; extra == "test"
